cicadad/__init__.py
cicadad/backend/__init__.py
cicadad/backend/backend-amd64.exe
cicadad/backend/backend-darwin-amd64
cicadad/backend/backend-darwin-arm64
cicadad/backend/backend-linux-32
cicadad/backend/backend-linux-amd64
cicadad/backend/backend-linux-arm
cicadad/backend/backend-linux-arm64
cicadad/configs/__init__.py
cicadad/core/__init__.py
cicadad/core/cli.py
cicadad/core/commands.py
cicadad/core/containers.py
cicadad/core/decorators.py
cicadad/core/engine.py
cicadad/core/runners.py
cicadad/core/scenario.py
cicadad/core/types.py
cicadad/metrics/__init__.py
cicadad/metrics/collectors.py
cicadad/metrics/console.py
cicadad/protos/__init__.py
cicadad/protos/backend_pb2.py
cicadad/protos/backend_pb2_grpc.py
cicadad/services/__init__.py
cicadad/services/backend.py
cicadad/templates/Dockerfile
cicadad/templates/__init__.py
cicadad/templates/backend.yaml
cicadad/templates/dev.dockerfile
cicadad/templates/job.yaml
cicadad/templates/local.dockerfile
cicadad/templates/redis.yaml
cicadad/templates/test.py
cicadad/util/__init__.py
cicadad/util/backoff.py
cicadad/util/console.py
cicadad/util/constants.py
cicadad/util/context.py
cicadad/util/printing.py
tests/__init__.py
tests/core/__init__.py
tests/core/test_commands.py
tests/core/test_decorators.py
tests/core/test_runners.py
tests/core/test_scenario.py
tests/services/__init__.py
tests/services/metrics/__init__.py
tests/services/metrics/test_console.py
cicadad-1.7.0.dist-info/LICENSE
cicadad-1.7.0.dist-info/METADATA
cicadad-1.7.0.dist-info/WHEEL
cicadad-1.7.0.dist-info/entry_points.txt
cicadad-1.7.0.dist-info/top_level.txt
cicadad-1.7.0.dist-info/RECORD
