Metadata-Version: 2.1
Name: cicadad
Version: 1.7.0
Summary: Library for running distributed Cicada tests
Home-page: https://github.com/cicadatesting/cicada-distributed
Author: Jeremy Herzog
Author-email: jeremyaherzog@gmail.com
License: UNKNOWN
Project-URL: Bug Tracker, https://github.com/cicadatesting/cicada-distributed/issues
Project-URL: Docsite, https://cicadatesting.github.io/cicada-distributed-docs/
Project-URL: Demos, https://github.com/cicadatesting/cicada-distributed-demos
Platform: UNKNOWN
Classifier: Programming Language :: Python :: 3
Classifier: License :: OSI Approved :: Apache Software License
Classifier: Operating System :: OS Independent
Requires-Python: >=3.6
Requires-Dist: docker (>=5.0.3)
Requires-Dist: click (>=8.0.4)
Requires-Dist: configobj (>=5.0.6)
Requires-Dist: pydantic (>=1.9.0)
Requires-Dist: grpcio (>=1.44.0)
Requires-Dist: protobuf (>=3.19.4)
Requires-Dist: blessed (>=1.19.1)
Requires-Dist: dask (>=2020.1.0)
Requires-Dist: distributed (>=2020.1.0)
Requires-Dist: rich (>=11.2.0)
